o2h/__init__.py
o2h/translator.py
o2h-2.0.3.dist-info/METADATA
o2h-2.0.3.dist-info/WHEEL
o2h-2.0.3.dist-info/entry_points.txt
o2h-2.0.3.dist-info/top_level.txt
o2h-2.0.3.dist-info/RECORD
