Metadata-Version: 2.1
Name: o2h
Version: 2.0.3
Summary: Publish obsidian to hexo github page
Author-email: Chivier Humber <chivier.humber@outlook.com>
Project-URL: Homepage, https://github.com/Chivier/H2O2H
Keywords: feed,reader,tutorial
Classifier: License :: OSI Approved :: MIT License
Classifier: Programming Language :: Python
Classifier: Programming Language :: Python :: 3
Requires-Python: >=3.9
Provides-Extra: dev
Requires-Dist: black ; extra == 'dev'
Requires-Dist: bumpver ; extra == 'dev'
Requires-Dist: isort ; extra == 'dev'
Requires-Dist: pip-tools ; extra == 'dev'
Requires-Dist: pytest ; extra == 'dev'
